mosaik_hdf5.py
mosaik_hdf5-0.4.dist-info/AUTHORS.txt
mosaik_hdf5-0.4.dist-info/LICENSE.txt
mosaik_hdf5-0.4.dist-info/METADATA
mosaik_hdf5-0.4.dist-info/WHEEL
mosaik_hdf5-0.4.dist-info/entry_points.txt
mosaik_hdf5-0.4.dist-info/top_level.txt
mosaik_hdf5-0.4.dist-info/RECORD
