Metadata-Version: 2.1
Name: mosaik-hdf5
Version: 0.4
Summary: Stores mosaik simulation data in an HDF5 database.
Home-page: https://gitlab.com/mosaik/mosaik-hdf5
Author: Stefan Scherfke
Author-email: mosaik@offis.de
License: UNKNOWN
Platform: UNKNOWN
Classifier: Development Status :: 4 - Beta
Classifier: Environment :: Console
Classifier: Intended Audience :: Science/Research
Classifier: License :: OSI Approved :: GNU Lesser General Public License v2 (LGPLv2)
Classifier: Natural Language :: English
Classifier: Operating System :: OS Independent
Classifier: Programming Language :: Python
Classifier: Programming Language :: Python :: 3
Classifier: Programming Language :: Python :: 3.7
Classifier: Programming Language :: Python :: 3.8
Classifier: Programming Language :: Python :: 3.9
Classifier: Topic :: Scientific/Engineering
License-File: LICENSE.txt
License-File: AUTHORS.txt
